ml_ibge_cities/__init__.py
ml_ibge_cities/admin.py
ml_ibge_cities/apps.py
ml_ibge_cities/forms.py
ml_ibge_cities/ibge.py
ml_ibge_cities/templates/ml_ibge_cities/ml_ibge_cities_change_form.html
ml_ibge_cities/templates/ml_ibge_cities/ml_ibge_cities_options.html
ml_ibge_cities-1.0.1.dist-info/LICENSE
ml_ibge_cities-1.0.1.dist-info/METADATA
ml_ibge_cities-1.0.1.dist-info/WHEEL
ml_ibge_cities-1.0.1.dist-info/top_level.txt
ml_ibge_cities-1.0.1.dist-info/RECORD
