Metadata-Version: 2.1
Name: ml-ibge-cities
Version: 1.0.1
Summary: A Django select cities web-based ibge.
Home-page: https://github.com/marlonleite/ml-ibge-cities
Author: Marlon Leite
Author-email: marlonleite@gmail.com
License: MIT
Classifier: Environment :: Web Environment
Classifier: Framework :: Django
Classifier: Framework :: Django :: 2
Classifier: Intended Audience :: Developers
Classifier: License :: OSI Approved :: BSD License
Classifier: Operating System :: OS Independent
Classifier: Programming Language :: Python :: 3 :: Only
Classifier: Programming Language :: Python :: 3.9
Classifier: Topic :: Internet :: WWW/HTTP
Classifier: Topic :: Internet :: WWW/HTTP :: Dynamic Content
Requires-Python: >=3.8
License-File: LICENSE
Requires-Dist: Django (>=2.1.4)
Requires-Dist: requests (>=2.28.1)
